{"skeleton": {"hash": "charparts1", "spine": "4.2.00", "x": 291, "y": 77, "width": 373, "height": 817, "images": "./", "audio": ""}, "bones": [{"name": "root"}, {"name": "b_hair_ahoge", "parent": "root", "x": 519.0, "y": 795}, {"name": "b_hair_bangs", "parent": "root", "x": 513.0, "y": 808}, {"name": "b_hair_top", "parent": "root", "x": 436.5, "y": 772.0}, {"name": "b_hair_bun", "parent": "root", "x": 351.5, "y": 642}, {"name": "b_hair_left", "parent": "root", "x": 367.5, "y": 710}, {"name": "b_hair_left_braid", "parent": "root", "x": 354.5, "y": 542}, {"name": "b_hair_right", "parent": "root", "x": 618.0, "y": 748}, {"name": "b_head", "parent": "root", "x": 510.0, "y": 642.5}, {"name": "b_neck_collar", "parent": "root", "x": 498.0, "y": 480.0}, {"name": "b_arm_l", "parent": "root", "x": 398.5, "y": 404.5}, {"name": "b_arm_r", "parent": "root", "x": 580.5, "y": 415.0}, {"name": "b_torso", "parent": "root", "x": 495.0, "y": 433.0}, {"name": "b_skirt", "parent": "root", "x": 490.5, "y": 310.0}, {"name": "b_legs", "parent": "root", "x": 482.5, "y": 202.0}, {"name": "b_shoes", "parent": "root", "x": 485.5, "y": 120.5}], "slots": [{"name": "shoes", "bone": "b_shoes", "attachment": "shoes"}, {"name": "legs", "bone": "b_legs", "attachment": "legs"}, {"name": "skirt", "bone": "b_skirt", "attachment": "skirt"}, {"name": "torso", "bone": "b_torso", "attachment": "torso"}, {"name": "arm_r", "bone": "b_arm_r", "attachment": "arm_r"}, {"name": "arm_l", "bone": "b_arm_l", "attachment": "arm_l"}, {"name": "neck_collar", "bone": "b_neck_collar", "attachment": "neck_collar"}, {"name": "head", "bone": "b_head", "attachment": "head"}, {"name": "hair_right", "bone": "b_hair_right", "attachment": "hair_right"}, {"name": "hair_left_braid", "bone": "b_hair_left_braid", "attachment": "hair_left_braid"}, {"name": "hair_left", "bone": "b_hair_left", "attachment": "hair_left"}, {"name": "hair_bun", "bone": "b_hair_bun", "attachment": "hair_bun"}, {"name": "hair_top", "bone": "b_hair_top", "attachment": "hair_top"}, {"name": "hair_bangs", "bone": "b_hair_bangs", "attachment": "hair_bangs"}, {"name": "hair_ahoge", "bone": "b_hair_ahoge", "attachment": "hair_ahoge"}], "skins": [{"name": "default", "attachments": {"hair_ahoge": {"hair_ahoge": {"x": 0, "y": 49.5, "width": 78, "height": 99}}, "hair_bangs": {"hair_bangs": {"x": 0, "y": -70.0, "width": 170, "height": 140}}, "hair_top": {"hair_top": {"x": 0, "y": 0, "width": 257, "height": 124}}, "hair_bun": {"hair_bun": {"x": 0, "y": -65.0, "width": 101, "height": 130}}, "hair_left": {"hair_left": {"x": 0, "y": -56.0, "width": 129, "height": 112}}, "hair_left_braid": {"hair_left_braid": {"x": 0, "y": -80.0, "width": 127, "height": 160}}, "hair_right": {"hair_right": {"x": 0, "y": -184.0, "width": 92, "height": 368}}, "head": {"head": {"x": 0, "y": 0, "width": 216, "height": 269}}, "neck_collar": {"neck_collar": {"x": 0, "y": 0, "width": 140, "height": 56}}, "arm_l": {"arm_l": {"x": 0, "y": 0, "width": 71, "height": 175}}, "arm_r": {"arm_r": {"x": 0, "y": 0, "width": 45, "height": 154}}, "torso": {"torso": {"x": 0, "y": 0, "width": 154, "height": 150}}, "skirt": {"skirt": {"x": 0, "y": 0, "width": 213, "height": 96}}, "legs": {"legs": {"x": 0, "y": 0, "width": 135, "height": 120}}, "shoes": {"shoes": {"x": 0, "y": 0, "width": 143, "height": 87}}}}], "animations": {"idle": {"bones": {"root": {"translate": [{"y": 0.0}, {"y": 0.8787, "time": 0.3}, {"y": 3.0, "time": 0.6}, {"y": 5.1213, "time": 0.9}, {"y": 6.0, "time": 1.2}, {"y": 5.1213, "time": 1.5}, {"y": 3.0, "time": 1.8}, {"y": 0.8787, "time": 2.1}, {"y": 0.0, "time": 2.4}], "scale": [{"x": 1.0, "y": 1.0}, {"time": 0.3, "x": 1.00088, "y": 1.00176}, {"time": 0.6, "x": 1.003, "y": 1.006}, {"time": 0.9, "x": 1.00512, "y": 1.01024}, {"time": 1.2, "x": 1.006, "y": 1.012}, {"time": 1.5, "x": 1.00512, "y": 1.01024}, {"time": 1.8, "x": 1.003, "y": 1.006}, {"time": 2.1, "x": 1.00088, "y": 1.00176}, {"time": 2.4, "x": 1.0, "y": 1.0}]}, "b_hair_ahoge": {"rotate": [{"value": 0.0}, {"time": 0.3, "value": 1.7678}, {"time": 0.6, "value": 2.5}, {"time": 0.9, "value": 1.7678}, {"time": 1.2, "value": 0.0}, {"time": 1.5, "value": -1.7678}, {"time": 1.8, "value": -2.5}, {"time": 2.1, "value": -1.7678}, {"time": 2.4, "value": -0.0}]}, "b_hair_bangs": {"rotate": [{"value": 0.5646}, {"time": 0.3, "value": 0.9829}, {"time": 0.6, "value": 0.8253}, {"time": 0.9, "value": 0.1843}, {"time": 1.2, "value": -0.5646}, {"time": 1.5, "value": -0.9829}, {"time": 1.8, "value": -0.8253}, {"time": 2.1, "value": -0.1843}, {"time": 2.4, "value": 0.5646}]}, "b_hair_top": {"rotate": [{"value": 0.4207}, {"time": 0.3, "value": 0.4885}, {"time": 0.6, "value": 0.2702}, {"time": 0.9, "value": -0.1065}, {"time": 1.2, "value": -0.4207}, {"time": 1.5, "value": -0.4885}, {"time": 1.8, "value": -0.2702}, {"time": 2.1, "value": 0.1065}, {"time": 2.4, "value": 0.4207}]}, "b_hair_bun": {"rotate": [{"value": 1.1995}, {"time": 0.3, "value": 0.8234}, {"time": 0.6, "value": -0.035}, {"time": 0.9, "value": -0.8729}, {"time": 1.2, "value": -1.1995}, {"time": 1.5, "value": -0.8234}, {"time": 1.8, "value": 0.035}, {"time": 2.1, "value": 0.8729}, {"time": 2.4, "value": 1.1995}]}, "b_hair_left": {"rotate": [{"value": 1.4549}, {"time": 0.3, "value": 0.5579}, {"time": 0.6, "value": -0.6658}, {"time": 0.9, "value": -1.4996}, {"time": 1.2, "value": -1.4549}, {"time": 1.5, "value": -0.5579}, {"time": 1.8, "value": 0.6658}, {"time": 2.1, "value": 1.4996}, {"time": 2.4, "value": 1.4549}]}, "b_hair_left_braid": {"rotate": [{"value": 1.3403}, {"time": 0.3, "value": -0.6276}, {"time": 0.6, "value": -2.2279}, {"time": 0.9, "value": -2.5231}, {"time": 1.2, "value": -1.3403}, {"time": 1.5, "value": 0.6276}, {"time": 1.8, "value": 2.2279}, {"time": 2.1, "value": 2.5231}, {"time": 2.4, "value": 1.3403}]}, "b_hair_right": {"rotate": [{"value": 0.0832}, {"time": 0.3, "value": -1.3542}, {"time": 0.6, "value": -1.9983}, {"time": 0.9, "value": -1.4718}, {"time": 1.2, "value": -0.0832}, {"time": 1.5, "value": 1.3542}, {"time": 1.8, "value": 1.9983}, {"time": 2.1, "value": 1.4718}, {"time": 2.4, "value": 0.0832}]}}}}}